{
  "kind": "collectionType",
  "collectionName": "modules",
  "info": {
    "singularName": "module",
    "pluralName": "modules",
    "displayName": "Module"
  },
  "options": {
    "draftAndPublish": true
  },
  "pluginOptions": {},
  "attributes": {
    "title": {
      "type": "string",
      "default": "Módulo sin Nombre.",
      "required": true,
      "minLength": 3
    },
    "description": {
      "type": "richtext",
      "default": "Descripción del Módulo",
      "required": false
    },
    "slug": {
      "type": "uid",
      "targetField": "title",
      "required": true
    },
    "course": {
      "type": "relation",
      "relation": "manyToOne",
      "target": "api::course.course",
      "inversedBy": "modules"
    },
    "lessons": {
      "type": "relation",
      "relation": "oneToMany",
      "target": "api::lesson.lesson",
      "mappedBy": "module"
    }
  }
}
